{
    "blocks": {
        "languageVersion": 0,
        "blocks": [
            {
                "type": "controls_repeat_ext",
                "id": ".zJzkNRSnRwxi?X1F(SX",
                "x": 109,
                "y": 259,
                "inputs": {
                    "TIMES": {
                        "shadow": {
                            "type": "math_number",
                            "id": "[hDS%RGy!+j#C*CELz=y",
                            "fields": {
                                "NUM": 10
                            }
                        }
                    }
                }
            },
            {
                "type": "game_loop",
                "id": "+d#{6]}hl)Kw/t[=oWSP",
                "x": 36,
                "y": 95
            }
        ]
    }
}